Metadata-Version: 1.1
Name: nested-namespace
Version: 0.0.1.post1
Summary: Simple nested Namespaces
Home-page: https://github.com/ntnn/python-nested_namespace
Author: Nelo-T. Wallus
Author-email: nelo@wallus.de
License: GPLv3
Keywords: nested recursive namespace namespaces
Platform: UNKNOWN
Classifier: Development Status :: 3 - Alpha
Classifier: Intended Audience :: Developers
Classifier: License :: OSI Approved :: GNU General Public License v3 or later (GPLv3+)
Classifier: Programming Language :: Python :: 3
Classifier: Programming Language :: Python :: 3.3
Classifier: Programming Language :: Python :: 3.4
Classifier: Programming Language :: Python :: 3.5
Classifier: Programming Language :: Python :: 3.6
